LICENSE
MANIFEST.in
setup.py
sortable/__init__.py
sortable/admin.py
sortable/conf.py
sortable/models.py
sortable/tests.py
sortable/static/sortable/css/inline-reorder.css
sortable/static/sortable/js/admin-list-reorder.js
sortable/static/sortable/js/inline-reorder.js
sortable/static/sortable/js/jquery-2.1.0.min.js
sortable/static/sortable/js/jquery-ui-1.10.4.custom.min.js
twentytab_sortable.egg-info/PKG-INFO
twentytab_sortable.egg-info/SOURCES.txt
twentytab_sortable.egg-info/dependency_links.txt
twentytab_sortable.egg-info/requires.txt
twentytab_sortable.egg-info/top_level.txt