Metadata-Version: 1.0
Name: twentytab-sortable
Version: 0.9
Summary: A django model and admin to create sortable items in django admin with jqueryui sortable method
Home-page: https://github.com/20tab/twentytab-sortable
Author: 20tab S.r.l.
Author-email: info@20tab.com
License: MIT License
Platform: UNKNOWN
